astrofm/__init__.py
astrofm/main.py
AstroFM-0.0.2.dist-info/LICENSE
AstroFM-0.0.2.dist-info/METADATA
AstroFM-0.0.2.dist-info/WHEEL
AstroFM-0.0.2.dist-info/top_level.txt
AstroFM-0.0.2.dist-info/RECORD
