Metadata-Version: 2.1
Name: AstroFM
Version: 0.0.2
Summary: Foundation Models for Astronomy
Author: Rithwik Gupta
Author-email: <rithwikca2020@gmail.com>
License: MIT
Classifier: Development Status :: 4 - Beta
Classifier: Intended Audience :: Science/Research
Classifier: License :: OSI Approved :: MIT License
Classifier: Programming Language :: Python :: 3
License-File: LICENSE
Requires-Dist: torch
Requires-Dist: numpy
